<?xml version="1.0" encoding="windows-1252" ?>
<!DOCTYPE ViewObject SYSTEM "jbo_03_01.dtd">
<!---->
<ViewObject
  xmlns="http://xmlns.oracle.com/bc4j"
  Name="NetworkLocatorVo"
  Version="12.2.1.12.24"
  InheritPersonalization="merge"
  BindingStyle="OracleName"
  CustomQuery="true"
  PageIterMode="Full"
  RowClass="com.iocl.customer.model.viewobject.NetworkLocatorVoRowImpl"
  ComponentClass="com.iocl.customer.model.viewobject.NetworkLocatorVoImpl">
  <DesignTime>
    <Attr Name="_isExpertMode" Value="true"/>
    <Attr Name="_codeGenFlag2" Value="Access|Coll|VarAccess"/>
    <Attr Name="_isCodegen" Value="true"/>
  </DesignTime>
  <Properties>
    <SchemaBasedProperties>
      <LABEL
        ResId="com.iocl.customer.model.viewobject.NetworkLocatorVo_LABEL"/>
    </SchemaBasedProperties>
  </Properties>
  <ViewAccessor
    Name="LocationCategoryVo1"
    ViewObjectName="com.iocl.customer.model.viewobject.LocationCategoryVo"
    RowLevelBinds="true"/>
  <SQLQuery><![CDATA[select rownum as dummy from dual]]></SQLQuery>
  <ViewAttribute
    Name="Dummy"
    IsUpdateable="false"
    IsPersistent="false"
    PrecisionRule="true"
    Precision="255"
    Type="java.lang.String"
    ColumnType="VARCHAR2"
    AliasName="DUMMY"
    Expression="DUMMY"
    SQLType="VARCHAR">
    <DesignTime>
      <Attr Name="_DisplaySize" Value="1"/>
    </DesignTime>
  </ViewAttribute>
  <ViewAttribute
    Name="NetworkType"
    IsSelected="false"
    IsPersistent="false"
    PrecisionRule="true"
    Precision="255"
    Type="java.lang.String"
    ColumnType="VARCHAR2"
    AliasName="VIEW_ATTR"
    SQLType="VARCHAR"/>
  <ViewAttribute
    Name="LocationSearch"
    IsSelected="false"
    IsPersistent="false"
    PrecisionRule="true"
    Precision="255"
    Type="java.lang.String"
    ColumnType="VARCHAR2"
    AliasName="VIEW_ATTR"
    SQLType="VARCHAR"/>
  <ViewAttribute
    Name="CategoryCode"
    IsSelected="false"
    IsPersistent="false"
    PrecisionRule="true"
    Precision="255"
    Type="java.lang.String"
    ColumnType="VARCHAR2"
    AliasName="VIEW_ATTR"
    SQLType="VARCHAR"/>
  <ViewAttribute
    Name="CategoryType"
    IsSelected="false"
    IsPersistent="false"
    PrecisionRule="true"
    Precision="255"
    Type="java.lang.String"
    ColumnType="VARCHAR2"
    AliasName="VIEW_ATTR"
    SQLType="VARCHAR"
    DefaultValue="adf.context.pageFlowScope.CategoryVal"/>
  <AttrArray Name="KeyAttributes">
    <Item Value="Dummy"/>
  </AttrArray>
  <ResourceBundle>
    <PropertiesBundle
      PropertiesFile="model.ModelBundle"/>
  </ResourceBundle>
</ViewObject>
