<?xml version="1.0" encoding="windows-1252" ?>
<!DOCTYPE ViewObject SYSTEM "jbo_03_01.dtd">
<!---->
<ViewObject
  xmlns="http://xmlns.oracle.com/bc4j"
  Name="CustomerGeneralVo"
  Version="12.2.1.12.24"
  InheritPersonalization="merge"
  BindingStyle="OracleName"
  CustomQuery="true"
  PageIterMode="Full"
  RowClass="com.iocl.customer.model.viewobject.CustomerGeneralVoRowImpl">
  <DesignTime>
    <Attr Name="_isExpertMode" Value="true"/>
    <Attr Name="_codeGenFlag2" Value="Access"/>
    <Attr Name="_isCodegen" Value="true"/>
  </DesignTime>
  <Properties>
    <SchemaBasedProperties>
      <LABEL
        ResId="com.iocl.customer.model.viewobject.CustomerGeneralVo_LABEL"/>
    </SchemaBasedProperties>
  </Properties>
  <ViewAccessor
    Name="SubsVouch_ConnVo1"
    ViewObjectName="com.iocl.customer.model.viewobject.SubsVouch_ConnVo"
    RowLevelBinds="true"/>
  <ViewAccessor
    Name="YesNo_GeneralVo1"
    ViewObjectName="com.iocl.customer.model.viewobject.YesNo_GeneralVo"
    RowLevelBinds="true"/>
  <ViewAccessor
    Name="LPG_POI_Vo1"
    ViewObjectName="com.iocl.customer.model.viewobject.LPG_POI_Vo"
    RowLevelBinds="true"/>
  <ViewAccessor
    Name="LPG_POA_Vo1"
    ViewObjectName="com.iocl.customer.model.viewobject.LPG_POA_Vo"
    RowLevelBinds="true"/>
  <ListBinding
    Name="LOV_ConnectionType"
    ListVOName="SubsVouch_ConnVo1"
    NullValueFlag="none"
    MRUCount="0">
    <AttrArray Name="AttrNames">
      <Item Value="ConnectionType"/>
    </AttrArray>
    <AttrArray Name="AttrExpressions"/>
    <AttrArray Name="ListAttrNames">
      <Item Value="ConnectionCode"/>
    </AttrArray>
    <AttrArray Name="ListDisplayAttrNames">
      <Item Value="ConnectionName"/>
    </AttrArray>
    <DisplayCriteria/>
  </ListBinding>
  <ListBinding
    Name="LOV_HotPlate"
    ListVOName="YesNo_GeneralVo1"
    NullValueFlag="none"
    MRUCount="0">
    <AttrArray Name="AttrNames">
      <Item Value="HotPlate"/>
    </AttrArray>
    <AttrArray Name="AttrExpressions"/>
    <AttrArray Name="ListAttrNames">
      <Item Value="Code"/>
    </AttrArray>
    <AttrArray Name="ListDisplayAttrNames">
      <Item Value="Name"/>
    </AttrArray>
    <DisplayCriteria/>
  </ListBinding>
  <ListBinding
    Name="LOV_ProofOfIdentityType"
    ListVOName="LPG_POI_Vo1"
    NullValueFlag="none"
    MRUCount="0">
    <AttrArray Name="AttrNames">
      <Item Value="ProofOfIdentityType"/>
    </AttrArray>
    <AttrArray Name="AttrExpressions"/>
    <AttrArray Name="DerivedAttrNames">
      <Item Value="POIDocType"/>
    </AttrArray>
    <AttrArray Name="ListAttrNames">
      <Item Value="Code"/>
      <Item Value="DocType"/>
    </AttrArray>
    <AttrArray Name="ListDisplayAttrNames">
      <Item Value="Description"/>
    </AttrArray>
    <DisplayCriteria/>
  </ListBinding>
  <ListBinding
    Name="LOV_ProofOfAddressType"
    ListVOName="LPG_POA_Vo1"
    NullValueFlag="none"
    MRUCount="0">
    <AttrArray Name="AttrNames">
      <Item Value="ProofOfAddressType"/>
    </AttrArray>
    <AttrArray Name="AttrExpressions"/>
    <AttrArray Name="DerivedAttrNames">
      <Item Value="POADocType"/>
    </AttrArray>
    <AttrArray Name="ListAttrNames">
      <Item Value="Code"/>
      <Item Value="DocType"/>
    </AttrArray>
    <AttrArray Name="ListDisplayAttrNames">
      <Item Value="Description"/>
    </AttrArray>
    <DisplayCriteria/>
  </ListBinding>
  <SQLQuery><![CDATA[select rownum srno from dual]]></SQLQuery>
  <ViewAttribute
    Name="Srno"
    IsPersistent="false"
    PrecisionRule="true"
    Type="java.math.BigDecimal"
    ColumnType="NUMBER"
    AliasName="SRNO"
    Expression="SRNO"
    SQLType="NUMERIC"/>
  <ViewAttribute
    Name="ConnectionType"
    IsSelected="false"
    IsPersistent="false"
    PrecisionRule="true"
    Precision="255"
    Type="java.lang.String"
    ColumnType="VARCHAR2"
    AliasName="VIEW_ATTR"
    SQLType="VARCHAR"
    LOVName="LOV_ConnectionType">
    <Properties>
      <SchemaBasedProperties>
        <CONTROLTYPE
          Value="radio"/>
      </SchemaBasedProperties>
    </Properties>
  </ViewAttribute>
  <ViewAttribute
    Name="EquipType"
    IsSelected="false"
    IsPersistent="false"
    PrecisionRule="true"
    Precision="255"
    Type="java.lang.String"
    ColumnType="VARCHAR2"
    AliasName="VIEW_ATTR"
    SQLType="VARCHAR"/>
  <ViewAttribute
    Name="HotPlate"
    IsSelected="false"
    IsPersistent="false"
    PrecisionRule="true"
    Precision="255"
    Type="java.lang.String"
    ColumnType="VARCHAR2"
    AliasName="VIEW_ATTR"
    SQLType="VARCHAR"
    LOVName="LOV_HotPlate">
    <Properties>
      <SchemaBasedProperties>
        <CONTROLTYPE
          Value="radio"/>
      </SchemaBasedProperties>
    </Properties>
  </ViewAttribute>
  <ViewAttribute
    Name="paymentMode"
    IsSelected="false"
    IsPersistent="false"
    PrecisionRule="true"
    Precision="255"
    Type="java.lang.String"
    ColumnType="VARCHAR2"
    AliasName="VIEW_ATTR"
    SQLType="VARCHAR"/>
  <ViewAttribute
    Name="PromoSelected"
    IsSelected="false"
    IsPersistent="false"
    PrecisionRule="true"
    Precision="255"
    Type="java.lang.String"
    ColumnType="VARCHAR2"
    AliasName="VIEW_ATTR"
    SQLType="VARCHAR"/>
  <ViewAttribute
    Name="ProofOfIdentityType"
    IsSelected="false"
    IsPersistent="false"
    PrecisionRule="true"
    Precision="255"
    Type="java.lang.String"
    ColumnType="VARCHAR2"
    AliasName="VIEW_ATTR"
    SQLType="VARCHAR"
    LOVName="LOV_ProofOfIdentityType">
    <Properties>
      <SchemaBasedProperties>
        <CONTROLTYPE
          Value="choice"/>
      </SchemaBasedProperties>
    </Properties>
  </ViewAttribute>
  <ViewAttribute
    Name="ProofOfIdentityNo"
    IsSelected="false"
    IsPersistent="false"
    PrecisionRule="true"
    Precision="255"
    Type="java.lang.String"
    ColumnType="VARCHAR2"
    AliasName="VIEW_ATTR"
    SQLType="VARCHAR"/>
  <ViewAttribute
    Name="POIDocType"
    IsSelected="false"
    IsPersistent="false"
    PrecisionRule="true"
    Precision="255"
    Type="java.lang.String"
    ColumnType="VARCHAR2"
    AliasName="VIEW_ATTR"
    SQLType="VARCHAR">
    <Dependencies>
      <Item
        Value="ProofOfIdentityType"/>
    </Dependencies>
  </ViewAttribute>
  <ViewAttribute
    Name="ProofOfAddressType"
    IsSelected="false"
    IsPersistent="false"
    PrecisionRule="true"
    Precision="255"
    Type="java.lang.String"
    ColumnType="VARCHAR2"
    AliasName="VIEW_ATTR"
    SQLType="VARCHAR"
    LOVName="LOV_ProofOfAddressType">
    <Properties>
      <SchemaBasedProperties>
        <CONTROLTYPE
          Value="choice"/>
      </SchemaBasedProperties>
    </Properties>
  </ViewAttribute>
  <ViewAttribute
    Name="ProofOfAddressNo"
    IsSelected="false"
    IsPersistent="false"
    PrecisionRule="true"
    Precision="255"
    Type="java.lang.String"
    ColumnType="VARCHAR2"
    AliasName="VIEW_ATTR"
    SQLType="VARCHAR"/>
  <ViewAttribute
    Name="POADocType"
    IsSelected="false"
    IsPersistent="false"
    PrecisionRule="true"
    Precision="255"
    Type="java.lang.String"
    ColumnType="VARCHAR2"
    AliasName="VIEW_ATTR"
    SQLType="VARCHAR">
    <Dependencies>
      <Item
        Value="ProofOfAddressType"/>
    </Dependencies>
  </ViewAttribute>
</ViewObject>
